weighted_tqdm/__init__.py
weighted_tqdm/weighted_tqdm.py
weighted_tqdm-0.9.dist-info/LICENSE
weighted_tqdm-0.9.dist-info/METADATA
weighted_tqdm-0.9.dist-info/WHEEL
weighted_tqdm-0.9.dist-info/top_level.txt
weighted_tqdm-0.9.dist-info/RECORD
