Metadata-Version: 2.1
Name: weighted-tqdm
Version: 0.9
Summary: weighted_tqdm allows for weighted iterations in tqdm progress bars.
Home-page: https://github.com/Ntropic/weighted_tqdm/archive/refs/tags/v0.9.tar.gz
Author: Michael Schilling
Author-email: michael@ntropic.de
Classifier: Programming Language :: Python :: 3
Classifier: License :: OSI Approved :: MIT License
Classifier: Operating System :: OS Independent
Requires-Python: >=3.6
License-File: LICENSE
Requires-Dist: numpy
Requires-Dist: tqdm
